{
  "vehicle": {
    "make": "AUDI",
    "model": "A3",
    "year_range": "2002-2008",
    "skus": [
      "FEA826 (11-450)"
    ],
    "description": "AUDI A3 2002-2008 9\" & HARNESS"
  },
  "search_queries_used": [
    "2002 AUDI A3 dashboard interior OEM"
  ],
  "download_date": "2026-02-16T13:39:58.633751",
  "images": [
    {
      "filename": "dashboard_01_0ac39628.jpg",
      "source_url": "https://cockpitdekor.com/10461-thickbox_default/audi-a3-typ-8p-2003-3d-interior-dashboard-trim-kit-dash-trim-dekor-14-parts.webp",
      "source_page": "",
      "search_engine": "google_direct",
      "search_query": "2002 AUDI A3 dashboard interior OEM",
      "width": 1228,
      "height": 1228,
      "file_size_bytes": 94024,
      "download_time": "2026-02-16T13:39:48.093944"
    },
    {
      "filename": "dashboard_02_65398263.jpg",
      "source_url": "https://cockpitdekor.com/11414-thickbox_default/audi-a3-typ-8p-2003-3d-interior-dashboard-trim-kit-dash-trim-dekor-14-parts.webp",
      "source_page": "",
      "search_engine": "google_direct",
      "search_query": "2002 AUDI A3 dashboard interior OEM",
      "width": 1024,
      "height": 1024,
      "file_size_bytes": 90390,
      "download_time": "2026-02-16T13:39:53.712985"
    },
    {
      "filename": "dashboard_03_600eea83.jpg",
      "source_url": "https://cockpitdekor.com/48-thickbox_default/audi-a3-typ-8p-2003-3d-interior-dashboard-trim-kit-dash-trim-dekor-14-parts.webp",
      "source_page": "",
      "search_engine": "google_direct",
      "search_query": "2002 AUDI A3 dashboard interior OEM",
      "width": 1422,
      "height": 1100,
      "file_size_bytes": 40398,
      "download_time": "2026-02-16T13:39:55.574955"
    },
    {
      "filename": "dashboard_04_9a432cb3.jpg",
      "source_url": "https://cockpitdekor.com/8271-thickbox_default/audi-a3-typ-8p-2006-2014-3d-interior-dashboard-trim-kit-dash-trim-dekor-31-parts.webp",
      "source_page": "",
      "search_engine": "google_direct",
      "search_query": "2002 AUDI A3 dashboard interior OEM",
      "width": 1228,
      "height": 950,
      "file_size_bytes": 54460,
      "download_time": "2026-02-16T13:39:57.828166"
    },
    {
      "filename": "dashboard_05_e0f5a609.jpg",
      "source_url": "https://i.ytimg.com/vi/J99dD98VO3M/maxresdefault.jpg",
      "source_page": "https://cabinet.matttroy.net/audi-a3-2002-interior-parts/",
      "search_engine": "bing",
      "search_query": "2002 AUDI A3 dashboard interior OEM",
      "width": 1280,
      "height": 720,
      "file_size_bytes": 77873,
      "download_time": "2026-02-16T13:39:58.633671"
    }
  ],
  "total_images": 5
}